{
  "the": "le",
  "a": "un",
  "an": "un",
  "and": "et",
  "or": "ou",
  "but": "mais",
  "not": "pas",
  "no": "non",
  "yes": "oui",
  "of": "de",
  "in": "dans",
  "on": "sur",
  "under": "sous",
  "over": "au-dessus",
  "with": "avec",
  "without": "sans",
  "for": "pour",
  "from": "de",
  "to": "vers",
  "at": "à",
  "by": "par",
  "into": "en",
  "between": "entre",
  "before": "avant",
  "after": "après",
  "near": "près",
  "far": "loin",
  "here": "ici",
  "there": "là",
  "when": "quand",
  "where": "où",
  "why": "pourquoi",
  "how": "comment",
  "who": "qui",
  "what": "quoi",
  "because": "parce que",
  "if": "si",
  "then": "alors",
  "now": "maintenant",
  "always": "toujours",
  "never": "jamais",
  "often": "souvent",
  "again": "encore",
  "still": "encore",
  "only": "seulement",
  "very": "très",
  "so": "si",
  "too": "aussi",
  "also": "aussi",
  "like": "comme",
  "i": "je",
  "you": "tu",
  "he": "il",
  "she": "elle",
  "it": "il",
  "we": "nous",
  "they": "ils",
  "me": "moi",
  "him": "lui",
  "her": "elle",
  "them": "eux",
  "my": "mon",
  "your": "ton",
  "his": "son",
  "its": "son",
  "our": "notre",
  "their": "leur",
  "this": "ce",
  "that": "que",
  "these": "ces",
  "those": "ces",
  "all": "tout",
  "some": "certains",
  "many": "beaucoup",
  "few": "peu",
  "each": "chaque",
  "every": "chaque",
  "one": "un",
  "two": "deux",
  "three": "trois",
  "four": "quatre",
  "five": "cinq",
  "six": "six",
  "seven": "sept",
  "eight": "huit",
  "nine": "neuf",
  "ten": "dix",
  "hundred": "cent",
  "thousand": "mille",
  "first": "premier",
  "last": "dernier",
  "be": "être",
  "is": "est",
  "am": "suis",
  "are": "sont",
  "was": "était",
  "were": "étaient",
  "been": "été",
  "have": "avoir",
  "has": "a",
  "had": "avait",
  "do": "faire",
  "does": "fait",
  "did": "fit",
  "go": "aller",
  "goes": "va",
  "went": "alla",
  "gone": "parti",
  "come": "venir",
  "came": "vint",
  "say": "dire",
  "says": "dit",
  "said": "dit",
  "see": "voir",
  "saw": "vit",
  "seen": "vu",
  "look": "regarder",
  "looked": "regarda",
  "watch": "regarder",
  "watched": "regardait",
  "find": "trouver",
  "found": "trouva",
  "give": "donner",
  "gave": "donna",
  "take": "prendre",
  "took": "prit",
  "make": "faire",
  "made": "fit",
  "know": "savoir",
  "knew": "savait",
  "think": "penser",
  "thought": "pensa",
  "want": "vouloir",
  "wanted": "voulait",
  "love": "aimer",
  "loved": "aimait",
  "live": "vivre",
  "lived": "vivait",
  "sleep": "dormir",
  "slept": "dormit",
  "dreamed": "rêva",
  "eat": "manger",
  "ate": "mangea",
  "drink": "boire",
  "drank": "but",
  "run": "courir",
  "ran": "courut",
  "walk": "marcher",
  "walked": "marcha",
  "fly": "voler",
  "flew": "vola",
  "fall": "tomber",
  "fell": "tomba",
  "sing": "chanter",
  "sang": "chanta",
  "speak": "parler",
  "spoke": "parla",
  "whisper": "murmurer",
  "whispered": "murmura",
  "smile": "sourire",
  "smiled": "sourit",
  "laugh": "rire",
  "laughed": "rit",
  "cry": "pleurer",
  "cried": "pleura",
  "open": "ouvrir",
  "opened": "ouvrit",
  "close": "fermer",
  "closed": "ferma",
  "read": "lire",
  "write": "écrire",
  "wrote": "écrivit",
  "listen": "écouter",
  "listened": "écouta",
  "hear": "entendre",
  "heard": "entendit",
  "wait": "attendre",
  "waited": "attendit",
  "stay": "rester",
  "stayed": "resta",
  "leave": "partir",
  "left": "partit",
  "return": "retourner",
  "returned": "retourna",
  "carry": "porter",
  "carried": "portait",
  "hold": "tenir",
  "held": "tenait",
  "keep": "garder",
  "kept": "garda",
  "lose": "perdre",
  "lost": "perdu",
  "break": "briser",
  "broke": "brisa",
  "grow": "grandir",
  "grew": "grandit",
  "become": "devenir",
  "became": "devint",
  "begin": "commencer",
  "began": "commença",
  "end": "finir",
  "ended": "finit",
  "day": "jour",
  "night": "nuit",
  "morning": "matin",
  "evening": "soir",
  "today": "aujourd'hui",
  "tomorrow": "demain",
  "yesterday": "hier",
  "year": "année",
  "month": "mois",
  "week": "semaine",
  "hour": "heure",
  "moment": "moment",
  "time": "temps",
  "spring": "printemps",
  "summer": "été",
  "autumn": "automne",
  "winter": "hiver",
  "world": "monde",
  "earth": "terre",
  "sky": "ciel",
  "sun": "soleil",
  "moon": "lune",
  "star": "étoile",
  "stars": "étoiles",
  "cloud": "nuage",
  "rain": "pluie",
  "snow": "neige",
  "wind": "vent",
  "storm": "tempête",
  "fire": "feu",
  "water": "eau",
  "river": "rivière",
  "sea": "mer",
  "ocean": "océan",
  "lake": "lac",
  "mountain": "montagne",
  "forest": "forêt",
  "tree": "arbre",
  "trees": "arbres",
  "leaf": "feuille",
  "leaves": "feuilles",
  "flower": "fleur",
  "grass": "herbe",
  "stone": "pierre",
  "road": "route",
  "path": "chemin",
  "bridge": "pont",
  "garden": "jardin",
  "house": "maison",
  "home": "maison",
  "door": "porte",
  "window": "fenêtre",
  "roof": "toit",
  "room": "chambre",
  "kitchen": "cuisine",
  "table": "table",
  "chair": "chaise",
  "bed": "lit",
  "book": "livre",
  "page": "page",
  "letter": "lettre",
  "word": "mot",
  "words": "mots",
  "story": "histoire",
  "song": "chanson",
  "voice": "voix",
  "sound": "bruit",
  "silence": "silence",
  "light": "lumière",
  "shadow": "ombre",
  "dark": "sombre",
  "darkness": "obscurité",
  "color": "couleur",
  "gold": "or",
  "silver": "argent",
  "red": "rouge",
  "blue": "bleu",
  "green": "vert",
  "yellow": "jaune",
  "white": "blanc",
  "black": "noir",
  "grey": "gris",
  "man": "homme",
  "woman": "femme",
  "child": "enfant",
  "children": "enfants",
  "boy": "garçon",
  "girl": "fille",
  "friend": "ami",
  "friends": "amis",
  "family": "famille",
  "mother": "mère",
  "father": "père",
  "sister": "soeur",
  "brother": "frère",
  "king": "roi",
  "queen": "reine",
  "heart": "coeur",
  "hand": "main",
  "eyes": "yeux",
  "eye": "oeil",
  "face": "visage",
  "head": "tête",
  "foot": "pied",
  "wing": "aile",
  "wings": "ailes",
  "animal": "animal",
  "bird": "oiseau",
  "cat": "chat",
  "dog": "chien",
  "fox": "renard",
  "wolf": "loup",
  "bear": "ours",
  "horse": "cheval",
  "mouse": "souris",
  "rabbit": "lapin",
  "owl": "chouette",
  "fish": "poisson",
  "old": "vieux",
  "new": "nouveau",
  "young": "jeune",
  "big": "grand",
  "small": "petit",
  "little": "petit",
  "long": "long",
  "short": "court",
  "high": "haut",
  "low": "bas",
  "good": "bon",
  "bad": "mauvais",
  "beautiful": "beau",
  "pretty": "joli",
  "happy": "heureux",
  "sad": "triste",
  "quiet": "calme",
  "loud": "fort",
  "slow": "lent",
  "slowly": "lentement",
  "fast": "vite",
  "warm": "chaud",
  "hot": "chaud",
  "cold": "froid",
  "sweet": "doux",
  "soft": "doux",
  "hard": "dur",
  "strong": "fort",
  "weak": "faible",
  "wise": "sage",
  "true": "vrai",
  "wrong": "faux",
  "full": "plein",
  "empty": "vide",
  "alone": "seul",
  "together": "ensemble",
  "secret": "secret",
  "magic": "magie",
  "treasure": "trésor",
  "mystery": "mystère",
  "dream": "rêve",
  "hope": "espoir",
  "fear": "peur",
  "joy": "joie",
  "life": "vie",
  "death": "mort",
  "nothing": "rien",
  "everything": "tout",
  "something": "quelque chose",
  "someone": "quelqu'un"
}
